nationstates/__init__.py
nationstates/exceptions.py
nationstates/info.py
nationstates/main.py
nationstates/objects.py
nationstates/nsapiwrapper/__init__.py
nationstates/nsapiwrapper/exceptions.py
nationstates/nsapiwrapper/info.py
nationstates/nsapiwrapper/main.py
nationstates/nsapiwrapper/objects.py
nationstates/nsapiwrapper/urls.py
nationstates/nsapiwrapper/utils.py
nationstates-3.1.4.dist-info/LICENSE.txt
nationstates-3.1.4.dist-info/METADATA
nationstates-3.1.4.dist-info/WHEEL
nationstates-3.1.4.dist-info/top_level.txt
nationstates-3.1.4.dist-info/RECORD
