Metadata-Version: 2.1
Name: nationstates
Version: 3.1.4
Summary: Nationstates API wrapper for python
Home-page: https://github.com/DolphDev/pynationstates
Author: Joshua W
Author-email: dolphdevgithub@gmail.com
License: MIT
Download-URL: https://github.com/DolphDev/pynationstates/releases/tag/3.1.4
Keywords: nationstates,api wrapper,api,Nationstates API,Nationstates API Wrapper,Wrapper,nationstates python bindings,web api,web wrapper
Platform: UNKNOWN
Classifier: License :: OSI Approved :: MIT License
Classifier: Operating System :: OS Independent
Classifier: Topic :: Utilities
Classifier: Programming Language :: Python :: 3.5
Classifier: Programming Language :: Python :: 3.6
Classifier: Programming Language :: Python :: 3.7
Classifier: Programming Language :: Python :: 3.8
License-File: LICENSE.txt
Requires-Dist: beautifulsoup4 (==4.9.3)
Requires-Dist: ezurl (==0.1.3.25)
Requires-Dist: requests (==2.25.*)
Requires-Dist: xmltodict (==0.12.0)
